pdfx/__init__.py
pdfx/backends.py
pdfx/cli.py
pdfx/colorprint.py
pdfx/downloader.py
pdfx/exceptions.py
pdfx/extractor.py
pdfx/threadpool.py
pdfx/libs/__init__.py
pdfx/libs/xmp.py
pdfx-1.4.1.dist-info/LICENSE
pdfx-1.4.1.dist-info/METADATA
pdfx-1.4.1.dist-info/WHEEL
pdfx-1.4.1.dist-info/entry_points.txt
pdfx-1.4.1.dist-info/top_level.txt
pdfx-1.4.1.dist-info/RECORD
